openai_priority_loadbalancer/__init__.py
openai_priority_loadbalancer/openai_priority_loadbalancer.py
openai_priority_loadbalancer-1.1.1.dist-info/LICENSE
openai_priority_loadbalancer-1.1.1.dist-info/METADATA
openai_priority_loadbalancer-1.1.1.dist-info/WHEEL
openai_priority_loadbalancer-1.1.1.dist-info/top_level.txt
openai_priority_loadbalancer-1.1.1.dist-info/RECORD
