Metadata-Version: 2.1
Name: openai_priority_loadbalancer
Version: 1.1.1
Summary: A multi-backend, prioritization load balancer for OpenAI
Author-email: Simon Kurtz <simonkurtz@gmail.com>
Project-URL: Changelog, https://github.com/simonkurtz-MSFT/python-openai-loadbalancer/releases
Project-URL: Documentation, https://github.com/simonkurtz-MSFT/python-openai-loadbalancer/blob/main/README.md
Project-URL: GitHub-Statistics, https://shields.io/github/stars/simonkurtz-MSFT/python-openai-loadbalancer?style=social
Project-URL: Homepage, https://github.com/simonkurtz-MSFT/python-openai-loadbalancer
Project-URL: Issues, https://github.com/simonkurtz-MSFT/python-openai-loadbalancer/issues
Project-URL: Repository, https://github.com/simonkurtz-MSFT/python-openai-loadbalancer
Classifier: Development Status :: 5 - Production/Stable
Classifier: License :: OSI Approved :: MIT License
Classifier: Operating System :: OS Independent
Classifier: Programming Language :: Python :: 3.8
Classifier: Programming Language :: Python :: 3.9
Classifier: Programming Language :: Python :: 3.10
Classifier: Programming Language :: Python :: 3.11
Classifier: Programming Language :: Python :: 3.12
Classifier: Programming Language :: Python :: 3.13
Requires-Python: >=3.8
License-File: LICENSE
Requires-Dist: httpx
